django_shts3.py
django_shts3-5.0.dist-info/LICENSE
django_shts3-5.0.dist-info/METADATA
django_shts3-5.0.dist-info/WHEEL
django_shts3-5.0.dist-info/entry_points.txt
django_shts3-5.0.dist-info/top_level.txt
django_shts3-5.0.dist-info/RECORD
