Metadata-Version: 2.1
Name: django-shts3
Version: 5.0
Summary: Start Django dev server faster
Home-page: https://gitlab.com/qwolphin/django-shts3
Author: Wolphin
Author-email: q@wolph.in
License: UNKNOWN
Platform: UNKNOWN
Classifier: Development Status :: 5 - Production/Stable
Classifier: Intended Audience :: Developers
Classifier: Natural Language :: English
Classifier: License :: OSI Approved :: MIT License
Classifier: Programming Language :: Python
Classifier: Programming Language :: Python :: 3
